IMGTgeneDL/IMGTgeneDL.py
IMGTgeneDL/__init__.py
IMGTgeneDL/c-region-variant-configs.tsv
IMGTgeneDL/species.tsv
IMGTgeneDL-0.6.1.dist-info/LICENSE
IMGTgeneDL-0.6.1.dist-info/METADATA
IMGTgeneDL-0.6.1.dist-info/WHEEL
IMGTgeneDL-0.6.1.dist-info/entry_points.txt
IMGTgeneDL-0.6.1.dist-info/top_level.txt
IMGTgeneDL-0.6.1.dist-info/RECORD
