Metadata-Version: 2.2
Name: IMGTgeneDL
Version: 0.6.1
Summary: Python script to download data from IMGT/GENE-DB
Home-page: https://github.com/JamieHeather/IMGTgeneDL
Author: Jamie Heather
Author-email: jheather@mgh.harvard.edu
License: : OSI Approved :: MIT License
Requires-Python: >=3.9
License-File: LICENSE
Requires-Dist: requests
Requires-Dist: importlib-resources>=1.1.0
